CHANGES.rst
LICENSE.rst
MANIFEST.in
README.rst
setup.cfg
setup.py
pyramid_modern/__init__.py
pyramid_modern.egg-info/PKG-INFO
pyramid_modern.egg-info/SOURCES.txt
pyramid_modern.egg-info/dependency_links.txt
pyramid_modern.egg-info/entry_points.txt
pyramid_modern.egg-info/not-zip-safe
pyramid_modern.egg-info/requires.txt
pyramid_modern.egg-info/top_level.txt
pyramid_modern/scaffolds/__init__.py
pyramid_modern/scaffolds/modern_scaffold/CHANGES.rst_tmpl
pyramid_modern/scaffolds/modern_scaffold/LICENSE.rst_tmpl
pyramid_modern/scaffolds/modern_scaffold/MANIFEST.in_tmpl
pyramid_modern/scaffolds/modern_scaffold/README.rst_tmpl
pyramid_modern/scaffolds/modern_scaffold/development.ini_tmpl
pyramid_modern/scaffolds/modern_scaffold/production.ini_tmpl
pyramid_modern/scaffolds/modern_scaffold/setup.cfg_tmpl
pyramid_modern/scaffolds/modern_scaffold/setup.py_tmpl
pyramid_modern/scaffolds/modern_scaffold/+package+/__init__.py_tmpl
pyramid_modern/scaffolds/modern_scaffold/+package+/resources.py_tmpl
pyramid_modern/scaffolds/modern_scaffold/+package+/tests.py_tmpl
pyramid_modern/scaffolds/modern_scaffold/+package+/views.py_tmpl
pyramid_modern/scaffolds/modern_scaffold/+package+/assets/favicon.ico
pyramid_modern/scaffolds/modern_scaffold/+package+/assets/bootstrap/css/bootstrap-responsive.css
pyramid_modern/scaffolds/modern_scaffold/+package+/assets/bootstrap/css/bootstrap-responsive.min.css
pyramid_modern/scaffolds/modern_scaffold/+package+/assets/bootstrap/css/bootstrap.css
pyramid_modern/scaffolds/modern_scaffold/+package+/assets/bootstrap/css/bootstrap.min.css
pyramid_modern/scaffolds/modern_scaffold/+package+/assets/bootstrap/css/bootstrap.min.responsive.css
pyramid_modern/scaffolds/modern_scaffold/+package+/assets/bootstrap/img/glyphicons-halflings-white.png
pyramid_modern/scaffolds/modern_scaffold/+package+/assets/bootstrap/img/glyphicons-halflings.png
pyramid_modern/scaffolds/modern_scaffold/+package+/assets/bootstrap/js/bootstrap.js
pyramid_modern/scaffolds/modern_scaffold/+package+/assets/bootstrap/js/bootstrap.min.js
pyramid_modern/scaffolds/modern_scaffold/+package+/assets/global/css/+package+.css
pyramid_modern/scaffolds/modern_scaffold/+package+/assets/global/css/ie6.css
