Metadata-Version: 1.0
Name: pyramid-modern
Version: 1.0.2
Summary: Modern Frontend Pyramid Scaffold
Home-page: https://github.com/KamiQuasi/pyramid_modern
Author: Luke Dary
Author-email: lukedary@gmail.com
License: UNKNOWN
Keywords: web pyramid pylons
Platform: UNKNOWN
Classifier: Framework :: Pylons
Classifier: Intended Audience :: Developers
Classifier: License :: OSI Approved :: MIT License
Classifier: Natural Language :: English
Classifier: Operating System :: MacOS
Classifier: Operating System :: Microsoft :: Windows
Classifier: Operating System :: Unix
Classifier: Programming Language :: Python
Classifier: Topic :: Internet :: WWW/HTTP
Classifier: Topic :: Internet :: WWW/HTTP :: WSGI :: Application
